Workbook

Sheet Dashboard
A1: Business Budget — Summary
A2: Figures pull live from the 'Budget' tab. Edit line items there.
A4: Annual income | B4: ='Budget'!$E$8 | E4: Cost category | F4: Annual cost | G4: % of total
A5: Total annual expenses | B5: ='Budget'!E34 | E5: Vehicle Costs | F5: ='Budget'!E17 | G5: =IF('Budget'!E34=0,"",F5/'Budget'!E34)
A6: Net annual profit | B6: ='Budget'!E35 | E6: Subscriptions | F6: ='Budget'!E22 | G6: =IF('Budget'!E34=0,"",F6/'Budget'!E34)
A7: Net monthly profit | B7: ='Budget'!E35/12 | E7: Business Costs & Licensing | F7: ='Budget'!E32 | G7: =IF('Budget'!E34=0,"",F7/'Budget'!E34)
A8: Average monthly expenses | B8: ='Budget'!E34/12 | E8: Total expenses | F8: =SUM(F5:F7)
A9: Net margin | B9: =IF('Budget'!$E$8=0,"",'Budget'!E35/'Budget'!$E$8)

Sheet Budget
A1: Business Budget & Cost Calculator
A2: Currency: AUD ($). Blue cells are editable — change Amount or Frequency and totals update automatically.
A4: Item | B4: Frequency | C4: Amount | D4: Monthly | E4: Annual | F4: % of Income | G4: Notes
A5: INCOME
A6: Business income / revenue | B6: Annually | C6: 100000 | D6: =IF(E6="","",E6/12) | E6: =IF(C6="","",C6*IF(B6="Weekly",52,IF(B6="Fortnightly",26,IF(B6="Monthly",12,IF(B6="Quarterly",4,IF(B6="Half-yearly",2,IF(B6="Annually",1,IF(B6="One-off",1,0)))))))) | G6: Client's stated annual earnings
A7: Other income | B7: Annually | C7: 0 | D7: =IF(E7="","",E7/12) | E7: =IF(C7="","",C7*IF(B7="Weekly",52,IF(B7="Fortnightly",26,IF(B7="Monthly",12,IF(B7="Quarterly",4,IF(B7="Half-yearly",2,IF(B7="Annually",1,IF(B7="One-off",1,0)))))))) | G7: Grants, interest, side jobs, etc.
A8: TOTAL INCOME | D8: =SUM(D6:D7) | E8: =SUM(E6:E7)
A10: VEHICLE COSTS
A11: Servicing & logbook | B11: Quarterly | C11: 375 | D11: =IF(E11="","",E11/12) | E11: =IF(C11="","",C11*IF(B11="Weekly",52,IF(B11="Fortnightly",26,IF(B11="Monthly",12,IF(B11="Quarterly",4,IF(B11="Half-yearly",2,IF(B11="Annually",1,IF(B11="One-off",1,0)))))))) | F11: =IF($E$8=0,"",E11/$E$8) | G11: ~$1,500 / year
A12: Tyres | B12: Annually | C12: 1200 | D12: =IF(E12="","",E12/12) | E12: =IF(C12="","",C12*IF(B12="Weekly",52,IF(B12="Fortnightly",26,IF(B12="Monthly",12,IF(B12="Quarterly",4,IF(B12="Half-yearly",2,IF(B12="Annually",1,IF(B12="One-off",1,0)))))))) | F12: =IF($E$8=0,"",E12/$E$8) | G12: Set of tyres incl. fitting
A13: Fuel | B13: Weekly | C13: 80 | D13: =IF(E13="","",E13/12) | E13: =IF(C13="","",C13*IF(B13="Weekly",52,IF(B13="Fortnightly",26,IF(B13="Monthly",12,IF(B13="Quarterly",4,IF(B13="Half-yearly",2,IF(B13="Annually",1,IF(B13="One-off",1,0)))))))) | F13: =IF($E$8=0,"",E13/$E$8) | G13: ~$80 / week
A14: Registration & CTP | B14: Annually | C14: 850 | D14: =IF(E14="","",E14/12) | E14: =IF(C14="","",C14*IF(B14="Weekly",52,IF(B14="Fortnightly",26,IF(B14="Monthly",12,IF(B14="Quarterly",4,IF(B14="Half-yearly",2,IF(B14="Annually",1,IF(B14="One-off",1,0)))))))) | F14: =IF($E$8=0,"",E14/$E$8) | G14: Annual rego renewal
A15: Vehicle insurance | B15: Monthly | C15: 120 | D15: =IF(E15="","",E15/12) | E15: =IF(C15="","",C15*IF(B15="Weekly",52,IF(B15="Fortnightly",26,IF(B15="Monthly",12,IF(B15="Quarterly",4,IF(B15="Half-yearly",2,IF(B15="Annually",1,IF(B15="One-off",1,0)))))))) | F15: =IF($E$8=0,"",E15/$E$8) | G15: Comprehensive cover
A16: Repairs & maintenance | B16: Annually | C16: 800 | D16: =IF(E16="","",E16/12) | E16: =IF(C16="","",C16*IF(B16="Weekly",52,IF(B16="Fortnightly",26,IF(B16="Monthly",12,IF(B16="Quarterly",4,IF(B16="Half-yearly",2,IF(B16="Annually",1,IF(B16="One-off",1,0)))))))) | F16: =IF($E$8=0,"",E16/$E$8) | G16: Wear & tear buffer
A17: Subtotal — Vehicle Costs | D17: =SUM(D11:D16) | E17: =SUM(E11:E16) | F17: =IF($E$8=0,"",E17/$E$8)
A19: SUBSCRIPTIONS
A20: ServiceM8 (job management) | B20: Monthly | C20: 99 | D20: =IF(E20="","",E20/12) | E20: =IF(C20="","",C20*IF(B20="Weekly",52,IF(B20="Fortnightly",26,IF(B20="Monthly",12,IF(B20="Quarterly",4,IF(B20="Half-yearly",2,IF(B20="Annually",1,IF(B20="One-off",1,0)))))))) | F20: =IF($E$8=0,"",E20/$E$8) | G20: Adjust to your plan tier
A21: Xero (accounting) | B21: Monthly | C21: 70 | D21: =IF(E21="","",E21/12) | E21: =IF(C21="","",C21*IF(B21="Weekly",52,IF(B21="Fortnightly",26,IF(B21="Monthly",12,IF(B21="Quarterly",4,IF(B21="Half-yearly",2,IF(B21="Annually",1,IF(B21="One-off",1,0)))))))) | F21: =IF($E$8=0,"",E21/$E$8) | G21: Standard plan
A22: Subtotal — Subscriptions | D22: =SUM(D20:D21) | E22: =SUM(E20:E21) | F22: =IF($E$8=0,"",E22/$E$8)
A24: BUSINESS COSTS & LICENSING
A25: Public liability insurance | B25: Annually | C25: 1100 | D25: =IF(E25="","",E25/12) | E25: =IF(C25="","",C25*IF(B25="Weekly",52,IF(B25="Fortnightly",26,IF(B25="Monthly",12,IF(B25="Quarterly",4,IF(B25="Half-yearly",2,IF(B25="Annually",1,IF(B25="One-off",1,0)))))))) | F25: =IF($E$8=0,"",E25/$E$8) | G25: $5m / $10m cover
A26: Business name registration | B26: Annually | C26: 60 | D26: =IF(E26="","",E26/12) | E26: =IF(C26="","",C26*IF(B26="Weekly",52,IF(B26="Fortnightly",26,IF(B26="Monthly",12,IF(B26="Quarterly",4,IF(B26="Half-yearly",2,IF(B26="Annually",1,IF(B26="One-off",1,0)))))))) | F26: =IF($E$8=0,"",E26/$E$8) | G26: ASIC renewal
A27: Trade licence / certification | B27: Annually | C27: 350 | D27: =IF(E27="","",E27/12) | E27: =IF(C27="","",C27*IF(B27="Weekly",52,IF(B27="Fortnightly",26,IF(B27="Monthly",12,IF(B27="Quarterly",4,IF(B27="Half-yearly",2,IF(B27="Annually",1,IF(B27="One-off",1,0)))))))) | F27: =IF($E$8=0,"",E27/$E$8) | G27: Licence renewal + CPD
A28: Phone & internet | B28: Monthly | C28: 110 | D28: =IF(E28="","",E28/12) | E28: =IF(C28="","",C28*IF(B28="Weekly",52,IF(B28="Fortnightly",26,IF(B28="Monthly",12,IF(B28="Quarterly",4,IF(B28="Half-yearly",2,IF(B28="Annually",1,IF(B28="One-off",1,0)))))))) | F28: =IF($E$8=0,"",E28/$E$8) | G28: Mobile + data
A29: Tools & equipment | B29: Annually | C29: 2000 | D29: =IF(E29="","",E29/12) | E29: =IF(C29="","",C29*IF(B29="Weekly",52,IF(B29="Fortnightly",26,IF(B29="Monthly",12,IF(B29="Quarterly",4,IF(B29="Half-yearly",2,IF(B29="Annually",1,IF(B29="One-off",1,0)))))))) | F29: =IF($E$8=0,"",E29/$E$8) | G29: Replacement / new tools
A30: Marketing & advertising | B30: Monthly | C30: 150 | D30: =IF(E30="","",E30/12) | E30: =IF(C30="","",C30*IF(B30="Weekly",52,IF(B30="Fortnightly",26,IF(B30="Monthly",12,IF(B30="Quarterly",4,IF(B30="Half-yearly",2,IF(B30="Annually",1,IF(B30="One-off",1,0)))))))) | F30: =IF($E$8=0,"",E30/$E$8) | G30: Website, ads, signage
A31: Bank & merchant fees | B31: Monthly | C31: 40 | D31: =IF(E31="","",E31/12) | E31: =IF(C31="","",C31*IF(B31="Weekly",52,IF(B31="Fortnightly",26,IF(B31="Monthly",12,IF(B31="Quarterly",4,IF(B31="Half-yearly",2,IF(B31="Annually",1,IF(B31="One-off",1,0)))))))) | F31: =IF($E$8=0,"",E31/$E$8) | G31: Card / EFTPOS fees
A32: Subtotal — Business Costs & Licensing | D32: =SUM(D25:D31) | E32: =SUM(E25:E31) | F32: =IF($E$8=0,"",E32/$E$8)
A34: TOTAL EXPENSES | D34: =D17+D22+D32 | E34: =E17+E22+E32 | F34: =IF($E$8=0,"",E34/$E$8)
A35: NET PROFIT (before tax) | D35: =$D$8-D34 | E35: =$E$8-E34 | F35: =IF($E$8=0,"",E35/$E$8)
A37: NOTE: All amounts are editable estimates — replace them with your real figures. 'NET PROFIT (before tax)' is income minus expenses and does NOT account for income tax, GST or super. Frequencies supported: Weekly, Fortnightly, Monthly, Quarterly, Half-yearly, Annually, One-off.
